IGVSessions/__init__.py
IGVSessions/__main__.py
camu/__init__.py
camu/__main__.py
detectFIO/__init__.py
detectFIO/__main__.py
findDupAndLinked/__init__.py
findDupAndLinked/__main__.py
preprocessing/__init__.py
preprocessing/__main__.py
snapshotIGV/__init__.py
snapshotIGV/__main__.py
camu-0.1.7.dist-info/LICENSE
camu-0.1.7.dist-info/METADATA
camu-0.1.7.dist-info/WHEEL
camu-0.1.7.dist-info/top_level.txt
camu-0.1.7.dist-info/RECORD
