Metadata-Version: 2.1
Name: camu
Version: 0.1.7
Summary: A package for filtering candidate mutations for spontaneous mutation rate estimates.
Home-page: https://gitlab.rlp.net/nruffini/camufi/tree/master
Author: Nicolas Ruffini
Author-email: ruffini@uni-mainz.de
License: UNKNOWN
Platform: UNKNOWN
Classifier: Programming Language :: Python :: 3
Classifier: License :: OSI Approved :: MIT License
Classifier: Operating System :: Unix
Requires-Dist: tqdm (>=4.32.1)
Requires-Dist: numpy (>=1.16.2)
Requires-Dist: pysam (>=0.15.2)
